afilter_vsp/__init__.py
afilter_vsp/server.py
afilter_vsp/version.py
afilter_vsp/protos/__init__.py
afilter_vsp/protos/afilter_vsp_pb2.py
afilter_vsp/protos/afilter_vsp_pb2_grpc.py
afilter_vsp/utils/Mask2polygon.py
afilter_vsp/utils/__init__.py
afilter_vsp/utils/check_health.py
afilter_vsp/utils/mask2polygon.py
afilter_vsp/utils/slide_inference.py
afilter_vsp/utils/transform.py
afilter_vsp-2.2.dist-info/METADATA
afilter_vsp-2.2.dist-info/WHEEL
afilter_vsp-2.2.dist-info/top_level.txt
afilter_vsp-2.2.dist-info/RECORD
